### Java三大特性

#### 封装

- 尽可能的隐藏内部细节，只保留一些对外的接口与外部发生联系，用户无需知道对象内部的细节

#### 继承

- 通过一个子类通过继承父类的非私有对象和方法，实现代码复用和拓展

#### 多态

- 多态分为编译时多态和运行时多态:

  - 编译时多态主要指方法的重载
  - 运行时多态指程序中定义的对象引用所指向的具体类型在运行期间才确定

  运行时多态有三个条件:

  - 继承
  - 覆盖(重写)
  - 向上转型

  这段代码会执行实际引用对象的play（）方法，而不是Instrument的play方法

  ```java
  public class Instrument {
      public void play() {
          System.out.println("Instrument is playing...");
      }
  }
  
  public class Wind extends Instrument {
      public void play() {
          System.out.println("Wind is playing...");
      }
  }
  
  public class Percussion extends Instrument {
      public void play() {
          System.out.println("Percussion is playing...");
      }
  }
  
  public class Music {
      public static void main(String[] args) {
          List<Instrument> instruments = new ArrayList<>();
          instruments.add(new Wind());
          instruments.add(new Percussion());
          for(Instrument instrument : instruments) {
              instrument.play();
          }
      }
  }
  ```

- 在new一个子类的时候，会先去调用父类的构造方法，然后再执行子类的构造方法

```java
public class Main {
    
    static class Animal{
        int weight = 10;

        public void print() {
            System.out.println("this Animal Print:" + weight);
        }

        public Animal() {
            print();
        }
    }

    static class Dog extends Animal {
        int weight = 20;

        @Override
        public void print() {
            System.out.println("this Dog Print:" + weight);
        }

        public Dog() {
            print();
        }
    }

    public static void main(String[] args) {
        Dog dog = new Dog();

        System.out.println("---------------");
        Animal dog222 = new Dog();
        Dog dog333 =  (Dog)dog222;
        
        System.out.println("---------------");
        Dog dog444 = (Dog)new Animal();

    }
}
```

结果：

```java
this Dog Print:0
this Dog Print:20
---------------
this Dog Print:0
this Dog Print:20
---------------
this Animal Print:10
```

1. 在new Dog的时候会先去执行父类Animal的构造方法，于是执行print函数，但由于Dog重写了print，因此调用的是Dog的print，但又由于Dog还没有初始化，因此weight为0
2. 然后执行dog的构造函数

-  

### 八大基本类型

- boolean 1
- byte 8
- char 16
- short 16
- int 32
- float 32
- long 64
- double 64



### 缓存池

- 在jdk8中，integer缓存池的大小默认为 -128 ～127
- 在缓冲池的范围内的基本类型自动装箱会调用valueOf()方法，因此多个Integer实例创建值相同的对象，那么就会引用相同的对象

```java
Integer m = 124;
Integer n = 124;
System.out.println(m == n); // true
```

- 如果在缓存池外

```java
Integer m = 128;
Integer n = 128;
System.out.println(m == n); // false
```

- new Integer()每次都会创建一个新的对象，而valueOf()则会判断是否在缓冲池内

```java
Integer new1 = new Integer(123);
Integer new2 = new Integer(123);
System.out.println(new1 == new2);    // false
Integer val1 = Integer.valueOf(123);
Integer val2 = Integer.valueOf(123);
System.out.println(val1 == val2);   // true
```



### String

- String被声明为final，内部使用char数组存储数据，该数据也声明为final，因此String不可变也不可继承

```java
public final class String
    implements java.io.Serializable, Comparable<String>, CharSequence {
    /** The value is used for character storage. */
    private final char value[];
```

- 不可变的好处
  1. StringPool的使用，如果一个String对象已经被创建过了，那么就会从StringPool取的引用，因为不可变所以才能这么用
  2. 不可变因此线程安全，可以在多个线程中安全使用
  3. 可以缓存hash值

- String 不可变，StringBuilder和StringBuffer可变
- StringBuilder性能高但线程不安全，StringBuffer线程安全但性能低



### 类加载的过程

1. java对象的创建过程

```java
 Person he = new Person();
```

- 1. 将硬盘上指定的Person.class文件加载进内存
  2. 执行方法的时候，在栈内存中开辟了该方法的空间，然后在该方法的栈区里分配了一个变量he
  3. 执行new，在堆内存中开辟一个实体类的空间，分配了一个内存地址
  4. 调用该实体类的构造函数，进行该类的初始化
  5. 该实体类的地址赋值给he，变量he就指向了该对象
  
- 上述步骤1其实就是类加载的过程，具体分为下列步骤
  1. 加载
     - 通过类的全限类名去磁盘将.class文件中的二进制字节流读入到内存中，将这个字节流转换成方法区的运行时数据结构，然后在堆中创建一个Class对象，作为方法区的访问入口
  1. 验证
     - 验证文件格式、元数据验证、字节码验证等，这一步是为了保证家加载.class文件符合jvm虚拟机的规范
  1. 准备
     - 在这个阶段会为静态变量去分配内存地址，并赋默认值，这里的默认值是0
  
  4. 解析
     - 去将符号引用解析为直接引用
     - 符号引用就是用一组符号去描述任何信息
     - 直接引用就是直接指向目标的指针
  
  5. 初始化
  
     - 对类的静态变量赋值
     - 执行类的静态代码块
  
     

### 类的初始化顺序

1. 父类（静态变量、静态代码块）
2. 子类（静态变量，静态代码块）
3. 父类（实例变量，普通语句块）
4. 父类（构造函数）
5. 子类（实例变量，普通语句块）
6. 子类（构造函数）



### 深拷贝和浅拷贝

- 深拷贝：
  - 拷贝对象和被拷贝对象引用不同的对象
- 浅拷贝
  - 拷贝对象和被拷贝对象引用相同的对象



### 反射

-  反射可以提供类运行时的信息
- 可以通过reflect类库取获取字段、类方法
- 反射很强大，但需要节制的去使用，使用反射会更加损耗性能，因为涉及动态解析，而且暴露了内部结构



### 泛型

- 作用&优点：
  - 编译时检查类型，从而减少运行时类型转换错误。
  - 编写更加通用的代码，减少重复工作

- 泛型的上下限

  ```java
  <?> 无限制通配符
  <? extends E> extends 关键字声明了类型的上界，表示参数化的类型可能是所指定的类型，或者是此类型的子类
  <? super E> super 关键字声明了类型的下界，表示参数化的类型可能是指定的类型，或者是此类型的父类
  ```

  

- 泛型擦除

  - 在编译后的泛型/使用了super声明的下界擦除为Object
  - 而使用了extend声明了上界的就为擦除为该上界

  ```java
  <T extend Person> 这里编译后就会擦除成Person
    <T super Person>这里编译后就会擦除成Object
  ```

  - 会自动产生桥接方法保证擦除后的代码仍然具有多态

  ```java
  class Person<T>{
    
    private T value;
    
    Public void setValue(T value){
       value=value;
    }
  }
  
  class Student extend Person<String>{
    private String value;
    
    @Override
      Public void setValue(String value){
      value=value;
    }
  }
  //这里在子类中我们设定父类的泛型为String，在编译后，父类的泛型会被擦除成Object，子类会用具体的类型，如下：
  class Person{
    
    private Object value;
    
    Public void setValue(Object ob){
      return value=ob;
    }
  }
  
  class Student extend Person<String>{
    private String value;
    
    @Override
      Public void setValue(String val){
      value=val;
    }
  }
  //这里可以看出，编译后setValue的入参类型与父类不同，这里按正常来说不是重写，而是重载
  //但在编译后的字节码可以看到，是有两个方法的
    public void setValue(java.lang.String);  //我们重写的setValue方法  
      Code:  
         0: aload_0  
         1: aload_1  
         2: invokespecial #16                 // Method com/tao/test/Pair.setValue:(Ljava/lang/Object;)V  
         5: return  
  
    public void setValue(java.lang.Object);   //编译时由编译器生成的桥方法  
      Code:  
         0: aload_0  
         1: aload_1  
         2: checkcast     #26                 // class java/util/Date  
         5: invokevirtual #30                 // Method setValue:(Ljava/util/Date; 去调用我们重写的setValue方法)V  
         8: return  
           //这里编译器自己生成了一个桥方法，子类真正覆盖父类的是这个桥方法，而在乔方法再去调用我们重写的方法
  ```

  

  

### 注解

- 作用：

  - 生成文档，通过代码里标识的元数据生成javadoc文档。

    编译检查，通过代码里标识的元数据让编译器在编译期间进行检查验证。

    编译时动态处理，编译时通过代码里标识的元数据动态处理，例如动态生成代码。

    运行时动态处理，运行时通过代码里标识的元数据动态处理，例如使用反射注入实例。

- 常见分类

  - **Java自带的标准注解**，包括`@Override`、`@Deprecated`和`@SuppressWarnings`，分别用于标明重写某个方法、标明某个类或方法过时、标明要忽略的警告，用这些注解标明后编译器就会进行检查。

    **元注解**，元注解是用于定义注解的注解，包括`@Retention`、`@Target`、`@Inherited`、`@Documented`，`@Retention`用于标明注解被保留的阶段，`@Target`用于标明注解使用的范围，`@Inherited`用于标明注解可继承，`@Documented`用于标明是否生成javadoc文档。

    **自定义注解**，可以根据自己的需求定义注解，并可用元注解对自定义注解进行注解。

    1. 通过反射去获取注解中的内容

- 使用场景：

  - AOP-通过切面实现解耦
